payment/__init__.py
payment/admin.py
payment/apps.py
payment/models.py
payment/payment_conf.py
payment/tests.py
payment/urls.py
payment/views.py
payment/migrations/0001_initial.py
payment/migrations/0002_paymentorder_date.py
payment/migrations/0003_auto_20210729_1132.py
payment/migrations/0004_alter_paymentorder_additional_info.py
payment/migrations/0005_subscription.py
payment/migrations/0006_subscription_customer_id.py
payment/migrations/0007_auto_20210921_0947.py
payment/migrations/0008_alter_subscription_end_date.py
payment/migrations/0009_subscription_subid.py
payment/migrations/0010_auto_20210921_1055.py
payment/migrations/0011_alter_paymentorder_name.py
payment/migrations/0012_webhookevent.py
payment/migrations/__init__.py
django_stripe_paypal-0.1.3.dist-info/LICENSE
django_stripe_paypal-0.1.3.dist-info/METADATA
django_stripe_paypal-0.1.3.dist-info/WHEEL
django_stripe_paypal-0.1.3.dist-info/top_level.txt
django_stripe_paypal-0.1.3.dist-info/RECORD
